cognitive_load_monitor/__init__.py
cognitive_load_monitor/monitor.py
cognitive_load_monitor-0.1.1.dist-info/licenses/LICENSE
cognitive_load_monitor-0.1.1.dist-info/licenses/NOTICE
cognitive_load_monitor-0.1.1.dist-info/METADATA
cognitive_load_monitor-0.1.1.dist-info/WHEEL
cognitive_load_monitor-0.1.1.dist-info/top_level.txt
cognitive_load_monitor-0.1.1.dist-info/RECORD
