Metadata-Version: 2.4
Name: cognitive-load-monitor
Version: 0.1.1
Summary: Lightweight cognitive load monitoring primitive for AI agents
Author: Synapse Data
Author-email: Ivan Lluch <contact@synapsedata.example>
License: Apache-2.0
Project-URL: Homepage, https://github.com/synapse-data/cognitive-load-monitor
Project-URL: Documentation, https://github.com/synapse-data/cognitive-load-monitor#readme
Project-URL: Repository, https://github.com/synapse-data/cognitive-load-monitor
Project-URL: Issues, https://github.com/synapse-data/cognitive-load-monitor/issues
Keywords: ai-agents,cognitive-load,monitoring,observability,orchestration,reliability,agent-infrastructure
Classifier: Development Status :: 4 - Beta
Classifier: Intended Audience :: Developers
Classifier: Topic :: Software Development :: Libraries :: Python Modules
Classifier: Topic :: Scientific/Engineering :: Artificial Intelligence
Classifier: Programming Language :: Python :: 3
Classifier: Programming Language :: Python :: 3.10
Classifier: Programming Language :: Python :: 3.11
Classifier: Programming Language :: Python :: 3.12
Classifier: Operating System :: OS Independent
Requires-Python: >=3.10
License-File: LICENSE
License-File: NOTICE
Dynamic: license-file
